pythree/__init__.py
pythree/sphere.py
pythree-0.0.0.dist-info/LICENSE
pythree-0.0.0.dist-info/METADATA
pythree-0.0.0.dist-info/WHEEL
pythree-0.0.0.dist-info/top_level.txt
pythree-0.0.0.dist-info/RECORD
