Metadata-Version: 2.1
Name: pythree
Version: 0.0.0
Summary: Creating 3d package with python
Home-page: https://github.com/rootjatin/pythree
Author: rootjatin (Jatin Sharma)
Author-email: <jatin100198@gmail.com>
License: UNKNOWN
Keywords: python,three dimensional,render,pythreemaker,3d,blender
Platform: UNKNOWN
Classifier: Development Status :: 1 - Planning
Classifier: Intended Audience :: Developers
Classifier: Programming Language :: Python :: 3
Classifier: Operating System :: Unix
Classifier: Operating System :: MacOS :: MacOS X
Classifier: Operating System :: Microsoft :: Windows
Requires-Dist: numpy
